MANIFEST.in
README.md
requirements.txt
setup.py
ssm_starter/__init__.py
ssm_starter/__main__.py
ssm_starter/ssm_starter.py
ssm_starter.egg-info/PKG-INFO
ssm_starter.egg-info/SOURCES.txt
ssm_starter.egg-info/dependency_links.txt
ssm_starter.egg-info/entry_points.txt
ssm_starter.egg-info/requires.txt
ssm_starter.egg-info/top_level.txt
test/__init__.py
test/script_test.py