Metadata-Version: 1.1
Name: ssm-starter
Version: 0.2.2
Summary: Read AWS SSM parameters into the environment, then start your app.
Home-page: https://github.com/billtrust/ssm-starter
Author: Doug Kerwin
Author-email: dwkerwin@gmail.com
License: MIT
Keywords: aws,ssm,aws-ssm,parameter-store
Platform: UNKNOWN
Classifier: Development Status :: 5 - Production/Stable
Classifier: Intended Audience :: Developers
Classifier: Natural Language :: English
Classifier: License :: OSI Approved :: MIT License
Classifier: Programming Language :: Python
Classifier: Programming Language :: Python :: 2.7
Classifier: Programming Language :: Python :: 3
Classifier: Programming Language :: Python :: 3.3
Classifier: Programming Language :: Python :: 3.4
Classifier: Programming Language :: Python :: 3.5
Classifier: Programming Language :: Python :: 3.6
